api/__init__.py
api/organizations.py
nexa_sdk-0.1.0.dist-info/licenses/LICENSE
nexa_sdk-0.1.0.dist-info/METADATA
nexa_sdk-0.1.0.dist-info/WHEEL
nexa_sdk-0.1.0.dist-info/top_level.txt
nexa_sdk-0.1.0.dist-info/RECORD
