Metadata-Version: 2.4
Name: nexa_sdk
Version: 0.1.0
Summary: Python SDK for Nexa APIs
Author-email: Nexa <contact@nexa.com>
License: MIT License
Classifier: Programming Language :: Python :: 3
Classifier: License :: OSI Approved :: MIT License
Classifier: Operating System :: OS Independent
Requires-Python: >=3.7
License-File: LICENSE
Requires-Dist: requests>=2.28.0
Dynamic: license-file
